fractal_tree/__init__.py
fractal_tree/branch.py
fractal_tree/mesh.py
fractal_tree/tree.py
fractal_tree/viz.py
fractal_tree-0.2.1.dist-info/LICENSE_fsahli
fractal_tree-0.2.1.dist-info/METADATA
fractal_tree-0.2.1.dist-info/WHEEL
fractal_tree-0.2.1.dist-info/top_level.txt
fractal_tree-0.2.1.dist-info/RECORD
