Metadata-Version: 2.1
Name: fractal-tree
Version: 0.2.1
Summary: Create a fractal tree over a surface discretized by triangles
Author: Francisco Sahli Costabal
Author-email: Henrik Finsberg <henriknf@simula.no>
License: Copyright 2023 Henrik Finsberg
License-File: LICENSE_fsahli
Requires-Dist: numpy
Requires-Dist: scipy
Requires-Dist: tqdm
Provides-Extra: all
Requires-Dist: fractal-tree[test] ; extra == 'all'
Requires-Dist: fractal-tree[docs] ; extra == 'all'
Requires-Dist: fractal-tree[pypi] ; extra == 'all'
Requires-Dist: fractal-tree[dev] ; extra == 'all'
Provides-Extra: demo
Requires-Dist: meshio ; extra == 'demo'
Requires-Dist: fenics-pulse ; extra == 'demo'
Requires-Dist: cardiac-geometries[gmsh] ; extra == 'demo'
Provides-Extra: dev
Requires-Dist: pdbpp ; extra == 'dev'
Requires-Dist: ipython ; extra == 'dev'
Requires-Dist: bump2version ; extra == 'dev'
Requires-Dist: pre-commit ; extra == 'dev'
Provides-Extra: docs
Requires-Dist: jupyter-book ; extra == 'docs'
Requires-Dist: sphinx-autoapi ; extra == 'docs'
Requires-Dist: fractal-tree[demo] ; extra == 'docs'
Provides-Extra: pypi
Requires-Dist: twine ; extra == 'pypi'
Requires-Dist: build ; extra == 'pypi'
Provides-Extra: test
Requires-Dist: pytest ; extra == 'test'
Requires-Dist: pytest-cov ; extra == 'test'
Requires-Dist: meshio ; extra == 'test'
